MANIFEST.in
README.md
requirements.txt
setup.py
joker/relational/__init__.py
joker/relational/interfaces.py
joker/relational/postgres.py
joker/relational/utils.py
joker/relational/tools/__init__.py
joker/relational/tools/sessions.py
joker/relational/tools/textual.py
joker_relational.egg-info/PKG-INFO
joker_relational.egg-info/SOURCES.txt
joker_relational.egg-info/dependency_links.txt
joker_relational.egg-info/namespace_packages.txt
joker_relational.egg-info/not-zip-safe
joker_relational.egg-info/requires.txt
joker_relational.egg-info/top_level.txt